cli.py
svg2stl_aviinfinity-0.0.2.dist-info/METADATA
svg2stl_aviinfinity-0.0.2.dist-info/WHEEL
svg2stl_aviinfinity-0.0.2.dist-info/entry_points.txt
svg2stl_aviinfinity-0.0.2.dist-info/top_level.txt
svg2stl_aviinfinity-0.0.2.dist-info/RECORD
