Metadata-Version: 2.1
Name: svg2stl_aviinfinity
Version: 0.0.2
Summary: A package to help you convert a SVG file to a 3D STL file
Author-email: aviinfinity <pi@aviparshan.com>
Project-URL: Homepage, https://github.com/avipars/svg2stl
Project-URL: Issues, https://github.com/avipars/svg2stl/issues
Keywords: stl,svg,svg2stl,3d
Classifier: Programming Language :: Python :: 3
Classifier: Operating System :: OS Independent
Requires-Python: >=3.9
Requires-Dist: numpy
Requires-Dist: gmsh
Requires-Dist: svg.path
